[
  {
    "ApiId": "/providers/microsoft.powerapps/apis/shared_sharepointonline",
    "CdpRevision": {
      "BaseUrl": "/",
      "LastChangedTimeString": "2023-11-29T21:23:53.4420000Z",
      "RevisionNumber": 1
    },
    "ConnectedDataSourceInfoNameMapping": {
      "{FilenameWithExtension}": "File name with extension",
      "{FullPath}": "Full Path",
      "{Identifier}": "Identifier",
      "{IsFolder}": "IsFolder",
      "{Link}": "Link to item",
      "{ModerationComment}": "Comments associated with the content approval of this list item",
      "{ModerationStatus}": "Content approval status",
      "{Name}": "Name",
      "{Path}": "Folder path",
      "{Thumbnail}": "Thumbnail",
      "{TriggerWindowEndToken}": "Trigger Window End Token",
      "{TriggerWindowStartToken}": "Trigger Window Start Token",
      "{VersionNumber}": "Version number",
      "actionItem": "actionItem",
      "active": "active",
      "assignment": "assignment",
      "assignment#Id": "assignment Id",
      "Author": "Created By",
      "Author#Claims": "Created By Claims",
      "autoNotify": "autoNotify",
      "ComplianceAssetId": "Compliance Asset Id",
      "Created": "Created",
      "createServiceRequest": "createServiceRequest",
      "dueInDays": "dueInDays",
      "Editor": "Modified By",
      "Editor#Claims": "Modified By Claims",
      "extendAttributes": "extendAttributes",
      "extendAttributesJSON": "extendAttributesJSON",
      "group": "group",
      "group#Id": "group Id",
      "groupValue": "groupValue",
      "ID": "ID",
      "isClearingOffice": "isClearingOffice",
      "isDesigneeACB": "isDesigneeACB",
      "isEmployeeACB": "isEmployeeACB",
      "isMSOACB": "isMSOACB",
      "isNAACB": "isNAACB",
      "isSupervisorACB": "isSupervisorACB",
      "mandatoryClearingOfficeACB": "mandatoryClearingOfficeACB",
      "Modified": "Modified",
      "notificationTemplate": "notificationTemplate",
      "OData__ColorTag": "Color Tag",
      "service": "service",
      "service#Id": "service Id",
      "service@odata.type": "service (service@odata.type)",
      "taskDetails": "taskDetails",
      "taskTitle": "taskTitle",
      "Title": "Title",
      "uid": "uid",
      "uidTask": "uidTask",
      "urlServiceRequest": "urlServiceRequest"
    },
    "DatasetName": "https://dod365.sharepoint-mil.us/sites/DCMA-SB-Collaboration",
    "EncodeDataset": true,
    "IsSampleData": false,
    "IsWritable": true,
    "Name": "OBOF-DS-templateOutProcessingChecklist",
    "Type": "ConnectedDataSourceInfo"
  }
]